{"display":{"firstperson_righthand":{"rotation":[7,11,14],"translation":[0,1,0]},"firstperson_lefthand":{"rotation":[7,11,14],"translation":[0,1,0]},"ground":{"translation":[0,1.75,0]},"gui":{"rotation":[27,140,1],"translation":[-0.25,-1,0],"scale":[2.38,2.38,2.38]},"fixed":{"scale":[2,2,2]}},"textures":{"particle":"reserv items/foot1/gold_apple_eat","texture":"reserv items/foot/gold_apple_unwrap"},"elements":[{"from":[6,7,7],"to":[10,9,9],"faces":{"north":{"uv":[0,9,4,11],"texture":"#texture"},"east":{"uv":[1,9,3,11],"texture":"#texture"},"south":{"uv":[0,9,4,11],"texture":"#texture"},"west":{"uv":[1,9,3,11],"texture":"#texture"},"up":{"uv":[0,5,4,7],"texture":"#texture"},"down":{"uv":[0,13,4,15],"texture":"#texture"}}},{"from":[7,7,6],"to":[9,9,10],"faces":{"north":{"uv":[1,9,3,11],"texture":"#texture"},"east":{"uv":[0,9,4,11],"texture":"#texture"},"south":{"uv":[1,9,3,11],"texture":"#texture"},"west":{"uv":[0,9,4,11],"texture":"#texture"},"up":{"uv":[1,4,3,8],"texture":"#texture"},"down":{"uv":[1,12,3,16],"texture":"#texture"}}},{"from":[6.5,6.5,6.5],"to":[9.5,9.5,9.5],"faces":{"north":{"uv":[0.5,8.5,3.5,11.5],"texture":"#texture"},"east":{"uv":[0.5,8.5,3.5,11.5],"texture":"#texture"},"south":{"uv":[0.5,8.5,3.5,11.5],"texture":"#texture"},"west":{"uv":[0.5,8.5,3.5,11.5],"texture":"#texture"},"up":{"uv":[0.5,4.5,3.5,7.5],"texture":"#texture"},"down":{"uv":[0.5,12.5,3.5,15.5],"texture":"#texture"}}},{"from":[8,9.5,7.5],"to":[8.5,10.5,8],"faces":{"north":{"uv":[0,2.5,0.5,3.5],"texture":"#texture"},"east":{"uv":[0,2.5,0.5,3.5],"texture":"#texture"},"south":{"uv":[0,2.5,0.5,3.5],"texture":"#texture"},"west":{"uv":[0,2.5,0.5,3.5],"texture":"#texture"},"up":{"uv":[0,2.5,0.5,3],"texture":"#texture"}}}]}